{
  "name": "0_max_mustermann",
  "description": "Eine Rolle, die beispielhaft das Format für ausgereiftere Rollen darstellt.",
  "demographic": {},
  "entries": [
    {
      "name": "0_max_mustermann_meta",
      "resource": {
        "identifier": "0_max_mustermann_meta.json",
        "content_type": "metadata"
      }
    },
    {
      "name": "0_max_mustermann_poi",
      "resource": {
        "identifier": "0_max_mustermann_poi.json",
        "content_type": "poi"
      }
    },
    {
      "name": "0_max_mustermann_diary",
      "resource": {
        "identifier": "0_max_mustermann_diary.txt",
        "content_type": "diary"
      }
    },
    {
      "name": "0_max_mustermann_picture",
      "resource": {
        "identifier": "0_max_mustermann_picture.png",
        "content_type": "picture"
      }
    }
  ],
  "scenarios": [
    "0_max_mustermann_parents_drown"
  ]
}
