[
  {
    "simpleName": "sea_level",
    "description": "Describes the average offset of the sea levels from the current value.",
    "minValue": -10,
    "maxValue": 30
  },
  {
    "simpleName": "energy_prod_coal",
    "description": "Describes how much energy is being produced by means of coal in GWh",
    "minValue": 0,
    "maxValue": 100
  },
  {
    "simpleName": "energy_prod_wind",
    "description": "Describes how much energy is being produced by means of wind in GWh",
    "minValue": 0,
    "maxValue": 100
  }
]